cellgeometry/Hello.py
cellgeometry/__init__.py
cellgeometry/pages/ Elastic_Metric_for_Cell_Boundary_Analysis.py
cellgeometry/pages/1-Load_Data.py
cellgeometry/pages/2-Cell_Shear.py
cellgeometry/pages/3-PCA.py
cellgeometry/utils/basic.py
cellgeometry/utils/data_utils.py
cellgeometry/utils/experimental.py
cellgeometry-0.1.2.dist-info/METADATA
cellgeometry-0.1.2.dist-info/WHEEL
cellgeometry-0.1.2.dist-info/RECORD
